flaglib/perf/__init__.py
flaglib/perf/py.typed
flaglib_perf-0.1.0.dist-info/METADATA
flaglib_perf-0.1.0.dist-info/WHEEL
flaglib_perf-0.1.0.dist-info/RECORD
