Metadata-Version: 2.4
Name: flaglib-perf
Version: 0.1.0
Summary: CLI options library for Linux's perf tool
Author-email: Yingchi Long <longyingchi24s@ict.ac.cn>
Requires-Python: >=3.12
